Heema/Heema.py
Heema/__init__.py
Heema/browser.py
Heema/pages.py
Heema/search_box.py
Heema/setup.py
Heema/test_browser_framework.py
Heema/toggle_button_test.py
Heema-2.0.0.9.dist-info/METADATA
Heema-2.0.0.9.dist-info/WHEEL
Heema-2.0.0.9.dist-info/top_level.txt
Heema-2.0.0.9.dist-info/RECORD
