Metadata-Version: 2.1
Name: Heema
Version: 2.0.0.9
Summary: A GUI framework built on top of tkinter, with new features.
Author: Федор Глеб | Abhay Gaur
Author-email: <abhay.12104531@gmail.com>
Keywords: Heema,heema,heema gui,HEEMA,heemagui,python,tkinter,modern,gui,tkintergui,browser
Classifier: Development Status :: 1 - Planning
Classifier: Intended Audience :: Developers
Classifier: Programming Language :: Python :: 3
Classifier: Operating System :: Unix
Classifier: Operating System :: MacOS :: MacOS X
Classifier: Operating System :: Microsoft :: Windows
Requires-Dist: BlurWindow
Requires-Dist: pillow
Requires-Dist: pyaudio
